spldb/__init__.py
spldb/_client.py
spldb/_collection.py
spldb/_database.py
spldb/_exceptions.py
spldb-0.0.3.dist-info/licenses/LICENSE
spldb-0.0.3.dist-info/METADATA
spldb-0.0.3.dist-info/WHEEL
spldb-0.0.3.dist-info/top_level.txt
spldb-0.0.3.dist-info/RECORD
