Metadata-Version: 2.4
Name: SPLDB
Version: 0.0.3
Summary: A Dropbox used as a Database.
Author: Alpha-O-Auro SpL
Author-email: imr@outlook.in
Requires-Python: >=3.6
License-File: LICENSE
Requires-Dist: dropbox
Dynamic: author
Dynamic: author-email
Dynamic: license-file
Dynamic: requires-dist
Dynamic: requires-python
Dynamic: summary
